elasticai/creator/__init__.py
elasticai/creator/function_utils.py
elasticai/creator/hw_accelerator_meta.py
elasticai/creator/hw_function_id.py
elasticai/creator/plugin.py
elasticai/creator/py.typed
elasticai/creator/template.py
elasticai/creator/arithmetic/__init__.py
elasticai/creator/arithmetic/fxp_arithmetic.py
elasticai/creator/arithmetic/fxp_converter.py
elasticai/creator/arithmetic/fxp_params.py
elasticai/creator/base_modules/__init__.py
elasticai/creator/base_modules/adaptable_silu.py
elasticai/creator/base_modules/conv1d.py
elasticai/creator/base_modules/hard_sigmoid.py
elasticai/creator/base_modules/hard_tanh.py
elasticai/creator/base_modules/identity.py
elasticai/creator/base_modules/linear.py
elasticai/creator/base_modules/lstm.py
elasticai/creator/base_modules/lstm_cell.py
elasticai/creator/base_modules/math_operations.py
elasticai/creator/base_modules/math_operations_torch.py
elasticai/creator/base_modules/prelu.py
elasticai/creator/base_modules/relu.py
elasticai/creator/base_modules/sigmoid.py
elasticai/creator/base_modules/silu.py
elasticai/creator/base_modules/tanh.py
elasticai/creator/file_generation/__init__.py
elasticai/creator/file_generation/in_memory_path.py
elasticai/creator/file_generation/on_disk_path.py
elasticai/creator/file_generation/resource_utils.py
elasticai/creator/file_generation/savable.py
elasticai/creator/file_generation/template.py
elasticai/creator/graph/__init__.py
elasticai/creator/graph/_types.py
elasticai/creator/graph/base_graph.py
elasticai/creator/graph/graph.py
elasticai/creator/graph/graph_iterators.py
elasticai/creator/graph/graph_rewriting.py
elasticai/creator/graph/name_generation.py
elasticai/creator/graph/subgraph_matching.py
elasticai/creator/graph/vf2/__init__.py
elasticai/creator/graph/vf2/matching.py
elasticai/creator/graph/vf2/state.py
elasticai/creator/ir/__init__.py
elasticai/creator/ir/base/__init__.py
elasticai/creator/ir/base/_has_data.py
elasticai/creator/ir/base/attribute.py
elasticai_creator-0.67.0.dist-info/METADATA
elasticai_creator-0.67.0.dist-info/WHEEL
elasticai_creator-0.67.0.dist-info/licenses/LICENSE
elasticai_creator-0.67.0.dist-info/RECORD
