Metadata-Version: 2.4
Name: elasticai.creator
Version: 0.67.0
Summary: Design, train and compile neural networks optimized specifically for FPGAs.
Author: Department Intelligent Embedded Systems - University Duisburg Essen
Maintainer-email: Lukas Einhaus <lukas.einhaus@uni-due.de>
License-File: LICENSE
Requires-Python: >=3.11
Requires-Dist: click>=8.1.7
Requires-Dist: cocotb>=2.0.0
Requires-Dist: numpy>=1.23.0
Requires-Dist: pytest>=7.0
Requires-Dist: tomlkit>=0.13.2
Requires-Dist: torch>=1.11
